vwr/__init__.py
vwr/client.js
vwr/driver.py
vwr/index.template
vwr/login.template
vwr/main.css
vwr/password.txt
vwr/server.py
vwr-0.1.14.dist-info/DESCRIPTION.rst
vwr-0.1.14.dist-info/METADATA
vwr-0.1.14.dist-info/RECORD
vwr-0.1.14.dist-info/WHEEL
vwr-0.1.14.dist-info/entry_points.txt
vwr-0.1.14.dist-info/metadata.json
vwr-0.1.14.dist-info/top_level.txt
